ryoma_ai/__init__.py
ryoma_ai/states.py
ryoma_ai/agent/__init__.py
ryoma_ai/agent/arrow_agent.py
ryoma_ai/agent/base.py
ryoma_ai/agent/chat_agent.py
ryoma_ai/agent/embedding.py
ryoma_ai/agent/factory.py
ryoma_ai/agent/kernel_node.py
ryoma_ai/agent/multi_agent_router.py
ryoma_ai/agent/pandas_agent.py
ryoma_ai/agent/python_agent.py
ryoma_ai/agent/resource_registry.py
ryoma_ai/agent/spark_agent.py
ryoma_ai/agent/sql.py
ryoma_ai/agent/validator.py
ryoma_ai/agent/workflow.py
ryoma_ai/agent/internals/enhanced_profiler.py
ryoma_ai/agent/internals/enhanced_sql_agent.py
ryoma_ai/agent/internals/metadata_agent.py
ryoma_ai/agent/internals/metadata_manager.py
ryoma_ai/agent/internals/query_planner.py
ryoma_ai/agent/internals/reforce_sql_agent.py
ryoma_ai/agent/internals/schema_linking_agent.py
ryoma_ai/agent/internals/sql_error_handler.py
ryoma_ai/agent/internals/sql_log_agent.py
ryoma_ai/agent/internals/sql_safety_validator.py
ryoma_ai/api/__init__.py
ryoma_ai/catalog/__init__.py
ryoma_ai/catalog/exceptions.py
ryoma_ai/catalog/indexer.py
ryoma_ai/cli/README.md
ryoma_ai/cli/__init__.py
ryoma_ai/cli/agent_manager.py
ryoma_ai/cli/app.py
ryoma_ai/cli/autocomplete_manager.py
ryoma_ai/cli/catalog_manager.py
ryoma_ai/cli/command_handler.py
ryoma_ai/cli/config_manager.py
ryoma_ai/cli/datasource_manager.py
ryoma_ai/cli/display_manager.py
ryoma_ai/cli/main.py
ryoma_ai/datasource/__init__.py
ryoma_ai/datasource/base.py
ryoma_ai/datasource/bigquery.py
ryoma_ai/datasource/duckdb.py
ryoma_ai/datasource/factory.py
ryoma_ai/datasource/file.py
ryoma_ai/datasource/iceberg.py
ryoma_ai/datasource/metadata.py
ryoma_ai/datasource/mysql.py
ryoma_ai/datasource/nosql.py
ryoma_ai/datasource/postgres.py
ryoma_ai/datasource/profiler.py
ryoma_ai/datasource/snowflake.py
ryoma_ai/datasource/sql.py
ryoma_ai/datasource/sqlite.py
ryoma_ai/embedding/__init__.py
ryoma_ai/embedding/client.py
ryoma_ai/embedding/config.py
ryoma_ai/embedding/factory.py
ryoma_ai/llm/__init__.py
ryoma_ai/llm/provider.py
ryoma_ai-0.1.5.dist-info/METADATA
ryoma_ai-0.1.5.dist-info/WHEEL
ryoma_ai-0.1.5.dist-info/entry_points.txt
ryoma_ai-0.1.5.dist-info/licenses/LICENSE
ryoma_ai-0.1.5.dist-info/RECORD
